[
    {
        "Index": 436,
        "Number": 437,
        "Name": "Bronzong",
        "STATS": {
            "HP": 67,
            "ATK": 89,
            "DEF": 116,
            "SPA": 79,
            "SPD": 116,
            "SPE": 33
        },
        "TYPE": [
            "Steel",
            "Psychic"
        ],
        "Ability": [
            "Levitate",
            "Heatproof",
            "Heavy Metal"
        ],
        "Tutor Moves": [
            "Signal Beam",
            "Iron Head",
            "Block",
            "Gravity",
            "Iron Defense",
            "Zen Headbutt",
            "Snore",
            "Trick",
            "Wonder Room",
            "Recycle",
            "Stealth Rock",
            "Sleep Talk",
            "Skill Swap"
        ],
        "Level Up Moves": [
            {
                "Level": 1,
                "Move": "Ally Switch"
            },
            {
                "Level": 1,
                "Move": "Tackle"
            },
            {
                "Level": 1,
                "Move": "Confusion"
            },
            {
                "Level": 5,
                "Move": "Imprison"
            },
            {
                "Level": 9,
                "Move": "Confuse Ray"
            },
            {
                "Level": 13,
                "Move": "Psywave"
            },
            {
                "Level": 15,
                "Move": "Hypnosis"
            },
            {
                "Level": 17,
                "Move": "Extrasensory"
            },
            {
                "Level": 19,
                "Move": "Feint Attack"
            },
            {
                "Level": 23,
                "Move": "Gyro Ball"
            },
            {
                "Level": 25,
                "Move": "Iron Defense"
            },
            {
                "Level": 27,
                "Move": "Zen Headbutt"
            },
            {
                "Level": 30,
                "Move": "Safeguard"
            },
            {
                "Level": 33,
                "Move": "Block"
            },
            {
                "Level": 37,
                "Move": "Hex"
            },
            {
                "Level": 41,
                "Move": "Future Sight"
            },
            {
                "Level": 45,
                "Move": "Payback"
            },
            {
                "Level": 49,
                "Move": "Heal Block"
            },
            {
                "Level": 53,
                "Move": "Psyshield Bash"
            },
            {
                "Level": 57,
                "Move": "Heal Bell"
            },
            {
                "Level": 61,
                "Move": "Heavy Slam"
            }
        ],
        "TM Moves": [
            {
                "Machine": "TM3",
                "Name": "Psyshock"
            },
            {
                "Machine": "TM4",
                "Name": "Calm Mind"
            },
            {
                "Machine": "TM6",
                "Name": "Toxic"
            },
            {
                "Machine": "TM10",
                "Name": "Hidden Power"
            },
            {
                "Machine": "TM11",
                "Name": "Sunny Day"
            },
            {
                "Machine": "TM15",
                "Name": "Hyper Beam"
            },
            {
                "Machine": "TM16",
                "Name": "Light Screen"
            },
            {
                "Machine": "TM17",
                "Name": "Protect"
            },
            {
                "Machine": "TM18",
                "Name": "Rain Dance"
            },
            {
                "Machine": "TM21",
                "Name": "Frustration"
            },
            {
                "Machine": "TM22",
                "Name": "SolarBeam"
            },
            {
                "Machine": "TM26",
                "Name": "Earthquake"
            },
            {
                "Machine": "TM27",
                "Name": "Return"
            },
            {
                "Machine": "TM29",
                "Name": "Psychic"
            },
            {
                "Machine": "TM30",
                "Name": "Shadow Ball"
            },
            {
                "Machine": "TM33",
                "Name": "Reflect"
            },
            {
                "Machine": "TM37",
                "Name": "Sandstorm"
            },
            {
                "Machine": "TM39",
                "Name": "Rock Tomb"
            },
            {
                "Machine": "TM42",
                "Name": "Facade"
            },
            {
                "Machine": "TM44",
                "Name": "Rest"
            },
            {
                "Machine": "TM56",
                "Name": "Weather Ball"
            },
            {
                "Machine": "TM57",
                "Name": "Charge Beam"
            },
            {
                "Machine": "TM64",
                "Name": "Explosion"
            },
            {
                "Machine": "TM68",
                "Name": "Giga Impact"
            },
            {
                "Machine": "TM69",
                "Name": "Rock Polish"
            },
            {
                "Machine": "TM70",
                "Name": "Flash"
            },
            {
                "Machine": "TM74",
                "Name": "Gyro Ball"
            },
            {
                "Machine": "TM77",
                "Name": "Psych Up"
            },
            {
                "Machine": "TM78",
                "Name": "Bulldoze"
            },
            {
                "Machine": "TM80",
                "Name": "Rock Slide"
            },
            {
                "Machine": "TM86",
                "Name": "Grass Knot"
            },
            {
                "Machine": "TM90",
                "Name": "Substitute"
            },
            {
                "Machine": "TM91",
                "Name": "Flash Cannon"
            },
            {
                "Machine": "TM92",
                "Name": "Trick Room"
            },
            {
                "Machine": "TM94",
                "Name": "Rock Smash"
            },
            {
                "Machine": "HM2",
                "Name": "Fly"
            },
            {
                "Machine": "HM4",
                "Name": "Strength"
            }
        ],
        "Other Form Index": [],
        "Evolutions": [],
        "Items": {
            "5": "Metal Coat"
        },
        "Defenses": {
            "Immune": [
                "Poison"
            ],
            "0.25x Resist": [
                "Psychic"
            ],
            "0.5x Resist": [
                "Normal",
                "Grass",
                "Ice",
                "Flying",
                "Rock",
                "Dragon",
                "Steel",
                "Fairy"
            ],
            "Neutral": [
                "Water",
                "Electric",
                "Fighting",
                "Bug"
            ],
            "2x Weak ": [
                "Fire",
                "Ground",
                "Ghost",
                "Dark"
            ],
            "4x Weak": []
        },
        "VANILLA STATS": {
            "HP": 67,
            "ATK": 89,
            "DEF": 116,
            "SPA": 79,
            "SPD": 116,
            "SPE": 33
        }
    }
]